{
    "name": "Radome_2_50.json",
    "N": 5,
    "x_ref": [
        0.0,
        -0.10754387014494846,
        0.35665330880152984,
        0.44472810868180795,
        0.803328593008542,
        1.0
    ],
    "y_ref": [
        0.0,
        0.5255939218374969,
        0.6678124003288575,
        0.658541820692125,
        0.4985930979757343,
        0.26465932141684045
    ],
    "curves": [
        {
            "type": "bezier",
            "d": 2,
            "x_ctr": [
                0.017577478532929097
            ],
            "y_ctr": [
                0.37944350606513777
            ]
        },
        {
            "type": "bezier",
            "d": 3,
            "x_ctr": [
                -0.20843824168769293,
                0.04618672113689318
            ],
            "y_ctr": [
                0.6434455475262962,
                0.7004915007003825
            ]
        },
        {
            "type": "droite"
        },
        {
            "type": "bezier",
            "d": 3,
            "x_ctr": [
                0.5862918605418208,
                0.7290764949456643
            ],
            "y_ctr": [
                0.6436410995201572,
                0.5869133778933167
            ]
        },
        {
            "type": "droite"
        }
    ]
}