{
    "name": "Radome_2_67.json",
    "N": 5,
    "x_ref": [
        0.0,
        -0.1387414474059511,
        0.0876977996994922,
        0.22193022406730203,
        0.7464950786654577,
        1.0
    ],
    "y_ref": [
        0.0,
        0.6780643226361509,
        0.8280311072575383,
        0.8581800332704105,
        0.46592249692336296,
        0.164387238030186
    ],
    "curves": [
        {
            "type": "bezier",
            "d": 2,
            "x_ctr": [
                -0.1738112689525711
            ],
            "y_ctr": [
                0.43234901360664973
            ]
        },
        {
            "type": "bezier",
            "d": 3,
            "x_ctr": [
                -0.11046211983754521,
                0.060186533086668145
            ],
            "y_ctr": [
                0.8762023058414583,
                0.821852010474203
            ]
        },
        {
            "type": "droite"
        },
        {
            "type": "bezier",
            "d": 3,
            "x_ctr": [
                0.38355086960988993,
                0.561557783363654
            ],
            "y_ctr": [
                0.8944804197646936,
                0.6858989570420285
            ]
        },
        {
            "type": "droite"
        }
    ]
}