{
    "name": "Radome_2_11.json",
    "N": 5,
    "x_ref": [
        0.0,
        -0.09234586071486584,
        0.26141070220334744,
        0.4368845267216982,
        0.8441283242971473,
        1.0
    ],
    "y_ref": [
        0.0,
        0.4513174301163591,
        0.6072552685675413,
        0.5639181974491934,
        0.3729377024799448,
        0.28737659334188165
    ],
    "curves": [
        {
            "type": "bezier",
            "d": 2,
            "x_ctr": [
                -0.23756509808877188
            ],
            "y_ctr": [
                0.37255218203255885
            ]
        },
        {
            "type": "bezier",
            "d": 3,
            "x_ctr": [
                0.0247548886422854,
                0.04972601572056261
            ],
            "y_ctr": [
                0.5148315329357165,
                0.6595353983131051
            ]
        },
        {
            "type": "droite"
        },
        {
            "type": "bezier",
            "d": 3,
            "x_ctr": [
                0.5649806902168065,
                0.6670469436936364
            ],
            "y_ctr": [
                0.5322820684560937,
                0.47014124676607705
            ]
        },
        {
            "type": "droite"
        }
    ]
}